flutter_gen/__init__.py
flutter_gen/__main__.py
flutter_gen/config/config_cmd.py
flutter_gen/core/command.py
flutter_gen/core/constants.py
flutter_gen/core/model.py
flutter_gen/create/create_cmd.py
flutter_gen/create/create_i18n.py
flutter_gen/figma/generate_text.py
flutter_gen/generate/generate_color_cmd.py
flutter_gen/generate/generate_font_cmd.py
flutter_gen/generate/generate_image_cmd.py
flutter_gen/generate/generate_localization_cmd.py
flutter_gen/generate/generate_object_freezed_cmd.py
flutter_gen/generate/generate_object_mapper_cmd.py
flutter_gen/generate/generate_r_cmd.py
flutter_gen/generate/generate_repo_cmd.py
flutter_gen/generate/generate_router_cmd.py
flutter_gen/generate/sync_cmd.py
flutter_gen/generate/watch_cmd.py
flutter_gen/intellji/install_cmd.py
flutter_gen/rename/config.py
flutter_gen/rename/rename_cmd.py
flutter_gen/template/api_template.py
flutter_gen/template/base_template.py
flutter_gen/template/component_cmd.py
flutter_gen/template/template_cmd.py
flutter_gen/utils/dart_helpers.py
flutter_gen/utils/debounce.py
flutter_gen/utils/file_helpers.py
flutter_gen/utils/file_replace.py
flutter_gen/utils/intellij.py
flutter_gen/utils/json_helpers.py
flutter_gen/utils/loader.py
flutter_gen/utils/pb.py
flutter_gen/utils/print.py
flutter_gen/utils/str_helpers.py
flutter_gen/utils/utils.py
flutter_gen_templates/__init__.py
flutter_gen_templates/api/api.dart
flutter_gen_templates/base/view.dart
flutter_gen_templates/base/viewmodel.dart
flutter_gen_templates/commands/api.dart
flutter_gen_templates/commands/json.dart
flutter_gen_templates/commands/mock.dart
flutter_gen_templates/commands/to_string.dart
flutter_gen_templates/gen/colors.dart
flutter_gen_templates/gen/component.dart
flutter_gen_templates/gen/entities.dart
flutter_gen_templates/gen/fonts.dart
flutter_gen_templates/gen/freezed.dart
flutter_gen_templates/gen/i18n.dart
flutter_gen_templates/gen/images.dart
flutter_gen_templates/gen/r.dart
flutter_gen_templates/gen/repository.dart
flutter_gen-2.2.0.dist-info/LICENSE
flutter_gen-2.2.0.dist-info/METADATA
flutter_gen-2.2.0.dist-info/WHEEL
flutter_gen-2.2.0.dist-info/entry_points.txt
flutter_gen-2.2.0.dist-info/top_level.txt
flutter_gen-2.2.0.dist-info/RECORD
